pybpod_gui_plugin_stmdiagram-1.0.0.dist-info/METADATA
pybpod_gui_plugin_stmdiagram-1.0.0.dist-info/RECORD
pybpod_gui_plugin_stmdiagram-1.0.0.dist-info/WHEEL
pybpod_gui_plugin_stmdiagram-1.0.0.dist-info/top_level.txt
pybpodgui_plugin_stmdiagram/__init__.py
pybpodgui_plugin_stmdiagram/settings.py
pybpodgui_plugin_stmdiagram/stmdiagram_window.py
pybpodgui_plugin_stmdiagram/models/__init__.py
pybpodgui_plugin_stmdiagram/models/session/__init__.py
pybpodgui_plugin_stmdiagram/models/session/session_treenode.py
