Metadata-Version: 2.1
Name: pybpod-gui-plugin-stmdiagram
Version: 1.0.0
Summary: State machine diagrams plugin
Home-page: https://bitbucket.org/fchampalimaud/pybpod-gui-plugin-stmdiagram
Author: Ricardo Jorge Vieira Ribeiro
Author-email: ricardo.ribeiro@research.fchampalimaud.org, ricardojvr@gmail.com
License: Copyright (C) 2007 Free Software Foundation, Inc. <http://fsf.org/>
Platform: UNKNOWN
Requires-Dist: pydot
